{
  "resourceType": "Observation",
  "id": "6e39ccf3-f997-4a2b-8f28-b4b71c778c70",
  "text": {
    "status": "generated",
    "div": "<div xmlns=\"http://www.w3.org/1999/xhtml\"><p><b>Generated Narrative</b></p><div style=\"display: inline-block; background-color: #d9e0e7; padding: 6px; margin: 4px; border: 1px solid #8da1b4; border-radius: 5px; line-height: 60%\"><p style=\"margin-bottom: 0px\">Resource \"6e39ccf3-f997-4a2b-8f28-b4b71c778c70\" </p></div><p><b>status</b>: final</p><p><b>category</b>: Laboratory <span style=\"background: LightGoldenRodYellow; margin: 4px; border: 1px solid khaki\"> (<a href=\"http://terminology.hl7.org/3.0.0/CodeSystem-observation-category.html\">Observation Category Codes</a>#laboratory)</span></p><p><b>code</b>: C Ab [Presence] in Serum or Plasma <span style=\"background: LightGoldenRodYellow; margin: 4px; border: 1px solid khaki\"> (<a href=\"https://loinc.org/\">LOINC</a>#945-6)</span></p><p><b>subject</b>: <a href=\"#Patient_2b90dd2b-2dab-4c75-9bb9-a355e07401e8\">See above (Patient/2b90dd2b-2dab-4c75-9bb9-a355e07401e8)</a></p><p><b>effective</b>: 2015-10-10T09:35:00+01:00</p><p><b>performer</b>: <a href=\"#Organization_45a5c5b1-4ec1-4d60-b4b2-ff5a84a41fd7\">See above (Organization/45a5c5b1-4ec1-4d60-b4b2-ff5a84a41fd7)</a></p><p><b>value</b>: Positive <span style=\"background: LightGoldenRodYellow; margin: 4px; border: 1px solid khaki\"> (<a href=\"https://browser.ihtsdotools.org/\">SNOMED CT</a>#10828004)</span></p></div>"
  },
  "status": "final",
  "category": [
    {
      "coding": [
        {
          "system": "http://terminology.hl7.org/CodeSystem/observation-category",
          "code": "laboratory"
        }
      ]
    }
  ],
  "code": {
    "coding": [
      {
        "system": "http://loinc.org",
        "code": "945-6",
        "display": "C Ab [Presence] in Serum or Plasma"
      }
    ]
  },
  "subject": {
    "reference": "Patient/2b90dd2b-2dab-4c75-9bb9-a355e07401e8"
  },
  "effectiveDateTime": "2015-10-10T09:35:00+01:00",
  "performer": [
    {
      "reference": "Organization/45a5c5b1-4ec1-4d60-b4b2-ff5a84a41fd7"
    }
  ],
  "valueCodeableConcept": {
    "coding": [
      {
        "system": "http://snomed.info/sct",
        "code": "10828004",
        "display": "Positive"
      }
    ]
  }
}